ulang/__init__.py
ulang/__main__.py
ulang/codegen/__init__.py
ulang/codegen/blockly.py
ulang/codegen/python.py
ulang/codegen/ulgen.py
ulang/parser/__init__.py
ulang/parser/core.py
ulang/parser/error.py
ulang/parser/lexer.py
ulang/parser/lrparser.py
ulang/runtime/__init__.py
ulang/runtime/env.py
ulang/runtime/main.py
ulang/runtime/repl.py
ulang/runtime/功用.py
mulang-0.0.13.dist-info/LICENSE
mulang-0.0.13.dist-info/METADATA
mulang-0.0.13.dist-info/WHEEL
mulang-0.0.13.dist-info/entry_points.txt
mulang-0.0.13.dist-info/top_level.txt
mulang-0.0.13.dist-info/RECORD
