Metadata-Version: 2.1
Name: mulang
Version: 0.0.13
Summary: 木兰编程语言演示
Home-page: https://github.com/MulanRevive/mulan
Author: 无名
Author-email: mulanrevive@gmail.com
License: UNKNOWN
Platform: UNKNOWN
Classifier: Programming Language :: Python :: 3
Classifier: License :: OSI Approved :: GNU General Public License (GPL)
Classifier: Operating System :: OS Independent
Requires-Dist: codegen
Requires-Dist: rply
